qat_rpc/__init__.py
qat_rpc/utils/__init__.py
qat_rpc/utils/constants.py
qat_rpc/utils/metrics.py
qat_rpc/zmq/__init__.py
qat_rpc/zmq/qat_commands.py
qat_rpc/zmq/receiver.py
qat_rpc/zmq/wrappers.py
qat_rpc-0.6.0.dist-info/LICENSE
qat_rpc-0.6.0.dist-info/METADATA
qat_rpc-0.6.0.dist-info/WHEEL
qat_rpc-0.6.0.dist-info/entry_points.txt
qat_rpc-0.6.0.dist-info/RECORD
