Metadata-Version: 2.1
Name: qat-rpc
Version: 0.6.0
Summary: RPC tooling for OQC QAT.
License: BSD-3-Clause
Author: Kajsa Eriksson Rosenqvist
Author-email: keriksson.rosenqvist@oxfordquantumcircuits.com
Requires-Python: >=3.10,<3.13
Classifier: License :: OSI Approved :: BSD License
Classifier: Programming Language :: Python :: 3
Classifier: Programming Language :: Python :: 3.10
Classifier: Programming Language :: Python :: 3.11
Classifier: Programming Language :: Python :: 3.12
Requires-Dist: prometheus-client (>=0.20.0,<0.21.0)
Requires-Dist: pyzmq (>=26.1.0,<27.0.0)
Requires-Dist: qat-compiler (>=2.3.0,<3.0.0)
